pacman/__init__.py
pacman/file_utils.py
pacman/models.py
pacman/pacman.py
pacman/prompt.py
pacman_prompts-2.3.3.dist-info/METADATA
pacman_prompts-2.3.3.dist-info/WHEEL
pacman_prompts-2.3.3.dist-info/top_level.txt
pacman_prompts-2.3.3.dist-info/RECORD
