Metadata-Version: 2.1
Name: pacman-prompts
Version: 2.3.3
Summary: Prompts As Code, man
Home-page: https://github.com/anishthite/pacman
Author: Anish Thite
Author-email: anishthite@gmail.com
License: MIT
Keywords: artificial intelligence,prompt engineering,prompt management
Classifier: Development Status :: 4 - Beta
Classifier: Intended Audience :: Developers
Classifier: Topic :: Scientific/Engineering :: Artificial Intelligence
Classifier: License :: OSI Approved :: MIT License
Classifier: Programming Language :: Python :: 3.6
Requires-Dist: openai
Requires-Dist: groq
Requires-Dist: anthropic
Requires-Dist: instructor
Requires-Dist: pyyaml
Requires-Dist: posthog
Requires-Dist: pydantic
